.gitignore
AUTHORS.txt
CHANGES.txt
GPL-LICENSE.txt
MIT-LICENSE.txt
README.txt
readme
setup.py
version.txt
js/__init__.py
js.jqueryui_selectmenu.egg-info/PKG-INFO
js.jqueryui_selectmenu.egg-info/SOURCES.txt
js.jqueryui_selectmenu.egg-info/dependency_links.txt
js.jqueryui_selectmenu.egg-info/entry_points.txt
js.jqueryui_selectmenu.egg-info/namespace_packages.txt
js.jqueryui_selectmenu.egg-info/not-zip-safe
js.jqueryui_selectmenu.egg-info/requires.txt
js.jqueryui_selectmenu.egg-info/top_level.txt
js/jqueryui_selectmenu/__init__.py
js/jqueryui_selectmenu/resources/README.txt
js/jqueryui_selectmenu/resources/jquery.ui.selectmenu.css
js/jqueryui_selectmenu/resources/jquery.ui.selectmenu.js