Metadata-Version: 1.0
Name: js.jqueryui_selectmenu
Version: 0.1
Summary: Fanstatic packaging of jqueryui_selectmenu
Home-page: https://github.com/do3cc/js.jqueryui_selectmenu
Author: Fanstatic Developers
Author-email: fanstatic@googlegroups.com
License: UNKNOWN
Platform: UNKNOWN
